{
    "manifests": {
        "dbp/relay-core-connector-oidc-bundle": {
            "manifest": {
                "bundles": {
                    "Dbp\\Relay\\CoreConnectorOidcBundle\\DbpRelayCoreConnectorOidcBundle": [
                        "all"
                    ]
                },
                "copy-from-recipe": {
                    "config/": "%CONFIG_DIR%/"
                },
                "env": {
                    "OIDC_SERVER_URL": "https://auth.your-server/auth/realms/your-realm",
                    "OIDC_FRONTEND_CLIENT_ID": "api-docs-client-id"
                }
            },
            "files": {
                "config/packages/dbp_relay_core_connector_oidc.yaml": {
                    "contents": [
                        "dbp_relay_core_connector_oidc:",
                        "  server_url: '%env(OIDC_SERVER_URL)%'",
                        "  frontend_client_id: '%env(OIDC_FRONTEND_CLIENT_ID)%'",
                        ""
                    ],
                    "executable": false
                }
            },
            "ref": "1a2f5a9ca501df1ca514f951cbee53af53ce0d2d"
        }
    }
}
